pyopenephys/__init__.py
pyopenephys/core.py
pyopenephys/openephys_tools.py
pyopenephys/tools.py
pyopenephys/version.py
pyopenephys-1.2.0.dist-info/LICENSE
pyopenephys-1.2.0.dist-info/METADATA
pyopenephys-1.2.0.dist-info/WHEEL
pyopenephys-1.2.0.dist-info/top_level.txt
pyopenephys-1.2.0.dist-info/RECORD
