Metadata-Version: 2.1
Name: pyopenephys
Version: 1.2.0
Summary: Python package for parsing Open Ephys data.
Home-page: https://github.com/CINPLA/py-open-ephys
Author: Alessio Buccino
Author-email: alessiob@ifi.uio.no
Classifier: Programming Language :: Python :: 3
Classifier: License :: OSI Approved :: GNU General Public License v3 (GPLv3)
Classifier: Operating System :: OS Independent
License-File: LICENSE
Requires-Dist: numpy
Requires-Dist: scipy
Requires-Dist: pyyaml
Requires-Dist: quantities
Requires-Dist: xmltodict
Requires-Dist: natsort
